backports-stubs/METADATA.toml
backports-stubs/__init__.pyi
backports-stubs/ssl_match_hostname/__init__.pyi
types_backports.ssl_match_hostname-3.7.4.4.dist-info/METADATA
types_backports.ssl_match_hostname-3.7.4.4.dist-info/WHEEL
types_backports.ssl_match_hostname-3.7.4.4.dist-info/top_level.txt
types_backports.ssl_match_hostname-3.7.4.4.dist-info/RECORD
